live/__init__.py
live/live-edit.css
live/live-edit.js
live/plugin.py
mkdocs_live_edit_plugin-0.3.1.data/data/live/live-edit.css
mkdocs_live_edit_plugin-0.3.1.data/data/live/live-edit.js
mkdocs_live_edit_plugin-0.3.1.dist-info/LICENSE.md
mkdocs_live_edit_plugin-0.3.1.dist-info/METADATA
mkdocs_live_edit_plugin-0.3.1.dist-info/WHEEL
mkdocs_live_edit_plugin-0.3.1.dist-info/entry_points.txt
mkdocs_live_edit_plugin-0.3.1.dist-info/top_level.txt
mkdocs_live_edit_plugin-0.3.1.dist-info/RECORD
