Metadata-Version: 2.2
Name: mkdocs-live-edit-plugin
Version: 0.3.1
Summary: An MkDocs plugin that allows editing pages directly from the browser.
Home-page: https://github.com/eddyluten/mkdocs-live-edit-plugin
Author: Eddy Luten
Author-email: eddyluten@gmail.com
License: MIT
Keywords: mkdocs python markdown editing authoring wiki server
Classifier: License :: OSI Approved :: MIT License
Classifier: Programming Language :: Python
Classifier: Programming Language :: Python :: 3 :: Only
Classifier: Topic :: Software Development :: Libraries :: Python Modules
Requires-Python: >=3.10
License-File: LICENSE.md
Requires-Dist: mkdocs
Requires-Dist: websockets>=14
Dynamic: author
Dynamic: author-email
Dynamic: classifier
Dynamic: description
Dynamic: description-content-type
Dynamic: home-page
Dynamic: keywords
Dynamic: license
Dynamic: requires-dist
Dynamic: requires-python
Dynamic: summary
